rtl/pc.v
// program counter:- 32 bit register, which will store the the next instruction adress

module pc(
    input wire rst,
    input wire clk,
    input wire [31:0]pc_next,
    output reg [31:0]pc
);

    always @(posedge clk) begin
        if(rst) pc <= 32'h0000_0000;
        else pc <= pc_next;
    end


endmodule

01_Programm counter/pc_tb.v
`timescale 1ns/1ps
module tb_pc;
    reg        clk, rst;
    reg [31:0] pc_next;
    wire[31:0] pc;

    pc dut (.clk(clk), .rst(rst), .pc_next(pc_next), .pc(pc));

    // 10 ns clock
    initial clk = 0;
    always #5 clk = ~clk;

    integer errors = 0;
    task check(input [31:0] exp);
        if (pc !== exp) begin
            $display("FAIL: pc=%0h expected=%0h", pc, exp);
            errors = errors + 1;
        end else
            $display("ok:   pc=%0h", pc);
    endtask

    initial begin
        $dumpfile("tb_pc.vcd");
        $dumpvars(0,tb_pc);

    end

    initial begin
        // --- reset ---
        rst=1; pc_next=32'h0; @(posedge clk); #1;
        check(32'h0000_0000);    // after reset, PC=0

        // --- advance PC+4 each cycle ---
        rst=0;
        pc_next=32'h0000_0004; @(posedge clk); #1; check(32'h0000_0004);
        pc_next=32'h0000_0008; @(posedge clk); #1; check(32'h0000_0008);
        pc_next=32'h0000_000C; @(posedge clk); #1; check(32'h0000_000C);

        // --- branch jump to address ---
        pc_next=32'h0000_0100; @(posedge clk); #1; check(32'h0000_0100);

        // --- reset again ---
        rst=1; pc_next=32'h0; @(posedge clk); #1; check(32'h0000_0000);

        if (errors==0) $display("ALL TESTS PASSED");
        else           $display("%0d TEST(S) FAILED", errors);
        $finish;
    end
endmodule

tb_pc.vcd
$date
	Sun Sep  6 14:03:44 2026
$end
$version
	Icarus Verilog
$end
$timescale
	1ps
$end
$scope module tb_pc $end
$var wire 32 ! pc [31:0] $end
$var reg 1 " clk $end
$var reg 32 # pc_next [31:0] $end
$var reg 1 $ rst $end
$var integer 32 % errors [31:0] $end
$scope module dut $end
$var wire 1 " clk $end
$var wire 32 & pc_next [31:0] $end
$var wire 1 $ rst $end
$var reg 32 ' pc [31:0] $end
$upscope $end
$scope task check $end
$var reg 32 ( exp [31:0] $end
$upscope $end
$upscope $end
$enddefinitions $end
$comment Show the parameter values. $end
$dumpall
$end
#0
$dumpvars
bx (
bx '
b0 &
b0 %
1$
b0 #
0"
bx !
$end
#5000
b0 !
b0 '
1"
#6000
b100 #
b100 &
0$
b0 (
#10000
0"
#15000
b100 !
b100 '
1"
#16000
b1000 #
b1000 &
b100 (
#20000
0"
#25000
b1000 !
b1000 '
1"
#26000
b1100 #
b1100 &
b1000 (
#30000
0"
#35000
b1100 !
b1100 '
1"
#36000
b100000000 #
b100000000 &
b1100 (
#40000
0"
#45000
b100000000 !
b100000000 '
1"
#46000
b0 #
b0 &
1$
b100000000 (
#50000
0"
#55000
b0 !
b0 '
1"
#56000
b0 (
