rtl/alu.v
// total 10 ta operation hobe...
// shamt ta b input er last 5 ta bit as, 2 to the power of 5 = 32.

module alu(
    input [31:0]a,
    input [31:0]b,
    input [3:0] alu_control,
    output reg [31:0] result,
    output zero
);
    wire [4:0]shamt = b[4:0]; // shift amount er short form.

always @(*) begin
    case (alu_control)
        4'b0000 : result = a + b; // add
        4'b0001 : result = a - b; // subtract
        4'b0010 : result = a & b; // and operation
        4'b0011 : result = a | b; // or operation
        4'b0100 : result = a ^ b; // xor operation
        4'b0101 : result = (($signed (a)) < ($signed (b))) ? 32'd1 : 32'd0; //slt :- set less than
        4'b0110 : result = a < b ? 32'd1 : 32'd0; //sltu :- set less than unsigned
        4'b0111 : result = a << shamt; // sll | shift left logical 
        4'b1000 : result = a >> shamt; // srl :- shift right logical
        4'b1001 : result = $signed(a)  >>> shamt; // sra :- shift right arithmatic.

        default : result = 32'd0;
    endcase    
    
end
    assign zero = (result==32'd0) ? 1'b1 : 1'b0;

endmodule

tb/alu_tb.v
`timescale 1ns/1ps

module alu_tb;

    reg [31:0] a, b;
    reg [3:0] alu_control;
    wire [31:0] result;
    wire zero;

    alu uut (
        .a(a),
        .b(b),
        .alu_control(alu_control),
        .result(result),
        .zero(zero)
    );

    task test;
        input [31:0] expected;
        begin
            #1;
            if (result !== expected)
                $display("FAIL | ctrl=%b a=%h b=%h result=%h expected=%h",
                         alu_control, a, b, result, expected);
            else
                $display("PASS | ctrl=%b a=%h b=%h result=%h",
                         alu_control, a, b, result);
        end
    endtask

    initial begin
        $dumpfile("waves/alu_tb.vcd");
        $dumpvars(0, alu_tb);

        // ADD
        a = 10; b = 20; alu_control = 4'b0000;
        test(30);

        // SUB
        a = 20; b = 10; alu_control = 4'b0001;
        test(10);

        // AND
        a = 32'hF0F0F0F0; b = 32'h0FF00FF0; alu_control = 4'b0010;
        test(32'h00F000F0);

        // OR
        a = 32'hF0F00000; b = 32'h0000FFFF; alu_control = 4'b0011;
        test(32'hF0F0FFFF);

        // XOR
        a = 32'hAAAAAAAA; b = 32'h55555555; alu_control = 4'b0100;
        test(32'hFFFFFFFF);

        // SLT
        a = -10; b = 5; alu_control = 4'b0101;
        test(1);

        // SLTU
        a = 5; b = 32'hFFFFFFFF; alu_control = 4'b0110;
        test(1);

        // SLL
        a = 1; b = 4; alu_control = 4'b0111;
        test(16);

        // SRL
        a = 32'h80000000; b = 4; alu_control = 4'b1000;
        test(32'h08000000);

        // SRA
        a = 32'h80000000; b = 4; alu_control = 4'b1001;
        test(32'hF8000000);

        // Zero flag
        a = 10; b = 10; alu_control = 4'b0001;
        #1;
        $display("ZERO TEST | result=%h zero=%b", result, zero);

        // Default
        a = 10; b = 20; alu_control = 4'b1111;
        test(0);

        $finish;
    end

endmodule

waves/alu_tb.vcd
$date
	Wed Sep  9 22:08:13 2026
$end
$version
	Icarus Verilog
$end
$timescale
	1ps
$end
$scope module alu_tb $end
$var wire 1 ! zero $end
$var wire 32 " result [31:0] $end
$var reg 32 # a [31:0] $end
$var reg 4 $ alu_control [3:0] $end
$var reg 32 % b [31:0] $end
$scope module uut $end
$var wire 32 & a [31:0] $end
$var wire 4 ' alu_control [3:0] $end
$var wire 32 ( b [31:0] $end
$var wire 1 ! zero $end
$var wire 5 ) shamt [4:0] $end
$var reg 32 * result [31:0] $end
$upscope $end
$scope task test $end
$var reg 32 + expected [31:0] $end
$upscope $end
$upscope $end
$enddefinitions $end
$comment Show the parameter values. $end
$dumpall
$end
#0
$dumpvars
b11110 +
b11110 *
b10100 )
b10100 (
b0 '
b1010 &
b10100 %
b0 $
b1010 #
b11110 "
0!
$end
#1000
b1010 )
b1010 "
b1010 *
b1010 +
b1 $
b1 '
b1010 %
b1010 (
b10100 #
b10100 &
#2000
b10000 )
b111100000000000011110000 "
b111100000000000011110000 *
b111100000000000011110000 +
b10 $
b10 '
b1111111100000000111111110000 %
b1111111100000000111111110000 (
b11110000111100001111000011110000 #
b11110000111100001111000011110000 &
#3000
b11111 )
b11110000111100001111111111111111 "
b11110000111100001111111111111111 *
b11110000111100001111111111111111 +
b11 $
b11 '
b1111111111111111 %
b1111111111111111 (
b11110000111100000000000000000000 #
b11110000111100000000000000000000 &
#4000
b10101 )
b11111111111111111111111111111111 "
b11111111111111111111111111111111 *
b11111111111111111111111111111111 +
b100 $
b100 '
b1010101010101010101010101010101 %
b1010101010101010101010101010101 (
b10101010101010101010101010101010 #
b10101010101010101010101010101010 &
#5000
b101 )
b1 "
b1 *
b1 +
b101 $
b101 '
b101 %
b101 (
b11111111111111111111111111110110 #
b11111111111111111111111111110110 &
#6000
b11111 )
b110 $
b110 '
b11111111111111111111111111111111 %
b11111111111111111111111111111111 (
b101 #
b101 &
#7000
b100 )
b10000 "
b10000 *
b10000 +
b111 $
b111 '
b100 %
b100 (
b1 #
b1 &
#8000
b1000000000000000000000000000 "
b1000000000000000000000000000 *
b1000000000000000000000000000 +
b1000 $
b1000 '
b10000000000000000000000000000000 #
b10000000000000000000000000000000 &
#9000
b11111000000000000000000000000000 "
b11111000000000000000000000000000 *
b11111000000000000000000000000000 +
b1001 $
b1001 '
#10000
1!
b1010 )
b0 "
b0 *
b1 $
b1 '
b1010 %
b1010 (
b1010 #
b1010 &
#11000
b10100 )
b0 +
b1111 $
b1111 '
b10100 %
b10100 (
