rtl/pc.v
// program counter:- 32 bit register, which will store the the next instruction adress

module pc(
    input wire rst,
    input wire clk,
    input wire [31:0]pc_next,
    output reg [31:0]pc
);

    always @(posedge clk) begin
        if(rst) pc <= 32'h0000_0000;
        else pc <= pc_next;
    end


endmodule

tb/pc_tb.v
`timescale 1ns/1ps

module pc_tb;

    reg        clk;
    reg        rst;
    reg [31:0] pc_next;
    wire [31:0] pc;

    pc dut (
        .clk     (clk),
        .rst     (rst),
        .pc_next (pc_next),
        .pc      (pc)
    );

    // 10 ns clock period
    initial clk = 1'b0;
    always #5 clk = ~clk;

    integer errors = 0;

    task check_pc;
        input [31:0] expected;
        begin
            if (pc !== expected) begin
                $display("FAIL t=%0t expected=%h got=%h",
                         $time, expected, pc);
                errors = errors + 1;
            end
            else begin
                $display("PASS t=%0t pc=%h", $time, pc);
            end
        end
    endtask

    initial begin
        $dumpfile("waves/pc.vcd");
        $dumpvars(0, pc_tb);

        // Reset test
        rst     = 1'b1;
        pc_next = 32'h0000_0000;

        @(posedge clk);
        #1;
        check_pc(32'h0000_0000);

        // Normal update tests
        rst     = 1'b0;

        pc_next = 32'h0000_0004;
        @(posedge clk);
        #1;
        check_pc(32'h0000_0004);

        pc_next = 32'h0000_0008;
        @(posedge clk);
        #1;
        check_pc(32'h0000_0008);

        // Branch/jump-like arbitrary address
        pc_next = 32'h0000_0100;
        @(posedge clk);
        #1;
        check_pc(32'h0000_0100);

        // Reset again
        rst = 1'b1;
        @(posedge clk);
        #1;
        check_pc(32'h0000_0000);

        if (errors == 0)
            $display("ALL TESTS PASSED");
        else
            $display("TESTS FAILED: %0d error(s)", errors);

        $finish;
    end

endmodule

waves/pc.vcd
$date
	Sun Sep  6 17:56:57 2026
$end
$version
	Icarus Verilog
$end
$timescale
	1ps
$end
$scope module pc_tb $end
$var wire 32 ! pc [31:0] $end
$var reg 1 " clk $end
$var reg 32 # pc_next [31:0] $end
$var reg 1 $ rst $end
$var integer 32 % errors [31:0] $end
$scope module dut $end
$var wire 1 " clk $end
$var wire 32 & pc_next [31:0] $end
$var wire 1 $ rst $end
$var reg 32 ' pc [31:0] $end
$upscope $end
$scope task check_pc $end
$var reg 32 ( expected [31:0] $end
$upscope $end
$upscope $end
$enddefinitions $end
$comment Show the parameter values. $end
$dumpall
$end
#0
$dumpvars
bx (
bx '
b0 &
b0 %
1$
b0 #
0"
bx !
$end
#5000
b0 !
b0 '
1"
#6000
b100 #
b100 &
0$
b0 (
#10000
0"
#15000
b100 !
b100 '
1"
#16000
b1000 #
b1000 &
b100 (
#20000
0"
#25000
b1000 !
b1000 '
1"
#26000
b100000000 #
b100000000 &
b1000 (
#30000
0"
#35000
b100000000 !
b100000000 '
1"
#36000
1$
b100000000 (
#40000
0"
#45000
b0 !
b0 '
1"
#46000
b0 (
